LianaiKouyu/README.md
LianaiKouyu/__init__.py
LianaiKouyu/__main__.py
LianaiKouyu/file.epub
LianaiKouyu/index.html
LianaiKouyu/css/__init__.py
LianaiKouyu/css/annotations.css
LianaiKouyu/css/main.css
LianaiKouyu/css/normalize.css
LianaiKouyu/css/popup.css
LianaiKouyu/font/__init__.py
LianaiKouyu/font/fontello.eot
LianaiKouyu/font/fontello.svg
LianaiKouyu/font/fontello.ttf
LianaiKouyu/font/fontello.woff
LianaiKouyu/img/__init__.py
LianaiKouyu/img/annotator-glyph-sprite.png
LianaiKouyu/img/annotator-icon-sprite.png
LianaiKouyu/img/apple-touch-icon.png
LianaiKouyu/img/cancelfullscreen.png
LianaiKouyu/img/close.png
LianaiKouyu/img/fullscreen.png
LianaiKouyu/img/loader.gif
LianaiKouyu/img/menu-icon.png
LianaiKouyu/img/save.png
LianaiKouyu/img/saved.png
LianaiKouyu/img/settings-s.png
LianaiKouyu/img/settings.png
LianaiKouyu/img/star.png
LianaiKouyu/js/__init__.py
LianaiKouyu/js/epub.js
LianaiKouyu/js/epub.min.js
LianaiKouyu/js/epub.min.map
LianaiKouyu/js/hooks.min.js
LianaiKouyu/js/hooks.min.map
LianaiKouyu/js/reader.js
LianaiKouyu/js/reader.js.map
LianaiKouyu/js/reader.min.js
LianaiKouyu/js/reader.min.map
LianaiKouyu/js/hooks/__init__.py
LianaiKouyu/js/hooks/extensions/__init__.py
LianaiKouyu/js/hooks/extensions/highlight.js
LianaiKouyu/js/libs/__init__.py
LianaiKouyu/js/libs/jquery.min.js
LianaiKouyu/js/libs/localforage.min.js
LianaiKouyu/js/libs/screenfull.js
LianaiKouyu/js/libs/screenfull.min.js
LianaiKouyu/js/libs/zip.min.js
LianaiKouyu/js/plugins/__init__.py
LianaiKouyu/js/plugins/hypothesis.js
LianaiKouyu/js/plugins/search.js
lianai_kouyu-2022.10.11.0.dist-info/METADATA
lianai_kouyu-2022.10.11.0.dist-info/WHEEL
lianai_kouyu-2022.10.11.0.dist-info/entry_points.txt
lianai_kouyu-2022.10.11.0.dist-info/top_level.txt
lianai_kouyu-2022.10.11.0.dist-info/RECORD
